[
  {
    "number": 42400,
    "action": "skipped_changed_since_review",
    "reason": "updated_at changed"
  },
  {
    "number": 67158,
    "action": "review_comment_synced",
    "reason": "updated durable Codex review comment"
  },
  {
    "number": 72092,
    "action": "review_comment_synced",
    "reason": "updated durable Codex review comment"
  },
  {
    "number": 72398,
    "action": "review_comment_synced",
    "reason": "updated durable Codex review comment"
  },
  {
    "number": 72497,
    "action": "review_comment_synced",
    "reason": "updated durable Codex review comment"
  },
  {
    "number": 72499,
    "action": "review_comment_synced",
    "reason": "updated durable Codex review comment"
  },
  {
    "number": 72500,
    "action": "review_comment_synced",
    "reason": "updated durable Codex review comment"
  },
  {
    "number": 72501,
    "action": "review_comment_synced",
    "reason": "updated durable Codex review comment"
  },
  {
    "number": 72504,
    "action": "review_comment_synced",
    "reason": "updated durable Codex review comment"
  },
  {
    "number": 72505,
    "action": "review_comment_synced",
    "reason": "updated durable Codex review comment"
  },
  {
    "number": 72507,
    "action": "review_comment_synced",
    "reason": "updated durable Codex review comment"
  },
  {
    "number": 72510,
    "action": "review_comment_synced",
    "reason": "updated durable Codex review comment"
  },
  {
    "number": 72511,
    "action": "review_comment_synced",
    "reason": "updated durable Codex review comment"
  },
  {
    "number": 72512,
    "action": "review_comment_synced",
    "reason": "updated durable Codex review comment"
  },
  {
    "number": 72513,
    "action": "review_comment_synced",
    "reason": "updated durable Codex review comment"
  },
  {
    "number": 72514,
    "action": "review_comment_synced",
    "reason": "updated durable Codex review comment"
  },
  {
    "number": 72515,
    "action": "review_comment_synced",
    "reason": "updated durable Codex review comment"
  },
  {
    "number": 72516,
    "action": "review_comment_synced",
    "reason": "updated durable Codex review comment"
  },
  {
    "number": 72517,
    "action": "review_comment_synced",
    "reason": "updated durable Codex review comment"
  },
  {
    "number": 72519,
    "action": "review_comment_synced",
    "reason": "updated durable Codex review comment"
  }
]