[
  {
    "number": 75,
    "action": "review_comment_synced",
    "reason": "updated durable Codex review comment"
  },
  {
    "number": 147,
    "action": "review_comment_synced",
    "reason": "updated durable Codex review comment"
  },
  {
    "number": 1210,
    "action": "review_comment_synced",
    "reason": "updated durable Codex review comment"
  },
  {
    "number": 6457,
    "action": "review_comment_synced",
    "reason": "updated durable Codex review comment"
  },
  {
    "number": 6599,
    "action": "review_comment_synced",
    "reason": "updated durable Codex review comment"
  },
  {
    "number": 6615,
    "action": "review_comment_synced",
    "reason": "updated durable Codex review comment"
  },
  {
    "number": 6792,
    "action": "review_comment_synced",
    "reason": "updated durable Codex review comment"
  },
  {
    "number": 6946,
    "action": "review_comment_synced",
    "reason": "updated durable Codex review comment"
  },
  {
    "number": 7057,
    "action": "review_comment_synced",
    "reason": "updated durable Codex review comment"
  },
  {
    "number": 7338,
    "action": "review_comment_synced",
    "reason": "updated durable Codex review comment"
  },
  {
    "number": 7359,
    "action": "review_comment_synced",
    "reason": "updated durable Codex review comment"
  },
  {
    "number": 7379,
    "action": "review_comment_synced",
    "reason": "updated durable Codex review comment"
  },
  {
    "number": 7403,
    "action": "review_comment_synced",
    "reason": "updated durable Codex review comment"
  },
  {
    "number": 7406,
    "action": "review_comment_synced",
    "reason": "updated durable Codex review comment"
  },
  {
    "number": 7424,
    "action": "review_comment_synced",
    "reason": "updated durable Codex review comment"
  },
  {
    "number": 7433,
    "action": "review_comment_synced",
    "reason": "updated durable Codex review comment"
  },
  {
    "number": 7661,
    "action": "review_comment_synced",
    "reason": "updated durable Codex review comment"
  },
  {
    "number": 8724,
    "action": "review_comment_synced",
    "reason": "updated durable Codex review comment"
  },
  {
    "number": 9394,
    "action": "review_comment_synced",
    "reason": "updated durable Codex review comment"
  },
  {
    "number": 9465,
    "action": "review_comment_synced",
    "reason": "updated durable Codex review comment"
  },
  {
    "number": 9607,
    "action": "review_comment_synced",
    "reason": "updated durable Codex review comment"
  },
  {
    "number": 10029,
    "action": "review_comment_synced",
    "reason": "updated durable Codex review comment"
  },
  {
    "number": 10137,
    "action": "review_comment_synced",
    "reason": "updated durable Codex review comment"
  },
  {
    "number": 10213,
    "action": "review_comment_synced",
    "reason": "updated durable Codex review comment"
  },
  {
    "number": 10354,
    "action": "review_comment_synced",
    "reason": "updated durable Codex review comment"
  },
  {
    "number": 10467,
    "action": "review_comment_synced",
    "reason": "updated durable Codex review comment"
  },
  {
    "number": 10872,
    "action": "review_comment_synced",
    "reason": "updated durable Codex review comment"
  },
  {
    "number": 11040,
    "action": "review_comment_synced",
    "reason": "updated durable Codex review comment"
  },
  {
    "number": 11055,
    "action": "review_comment_synced",
    "reason": "updated durable Codex review comment"
  },
  {
    "number": 11414,
    "action": "review_comment_synced",
    "reason": "updated durable Codex review comment"
  },
  {
    "number": 11473,
    "action": "review_comment_synced",
    "reason": "updated durable Codex review comment"
  },
  {
    "number": 11489,
    "action": "review_comment_synced",
    "reason": "updated durable Codex review comment"
  },
  {
    "number": 11655,
    "action": "review_comment_synced",
    "reason": "updated durable Codex review comment"
  },
  {
    "number": 11665,
    "action": "review_comment_synced",
    "reason": "updated durable Codex review comment"
  },
  {
    "number": 11703,
    "action": "review_comment_synced",
    "reason": "updated durable Codex review comment"
  },
  {
    "number": 11955,
    "action": "review_comment_synced",
    "reason": "updated durable Codex review comment"
  },
  {
    "number": 11960,
    "action": "review_comment_synced",
    "reason": "updated durable Codex review comment"
  },
  {
    "number": 12008,
    "action": "review_comment_synced",
    "reason": "updated durable Codex review comment"
  },
  {
    "number": 12047,
    "action": "review_comment_synced",
    "reason": "updated durable Codex review comment"
  },
  {
    "number": 12198,
    "action": "review_comment_synced",
    "reason": "updated durable Codex review comment"
  },
  {
    "number": 12219,
    "action": "review_comment_synced",
    "reason": "updated durable Codex review comment"
  },
  {
    "number": 12398,
    "action": "review_comment_synced",
    "reason": "updated durable Codex review comment"
  },
  {
    "number": 12441,
    "action": "review_comment_synced",
    "reason": "updated durable Codex review comment"
  },
  {
    "number": 12505,
    "action": "review_comment_synced",
    "reason": "updated durable Codex review comment"
  },
  {
    "number": 12508,
    "action": "review_comment_synced",
    "reason": "updated durable Codex review comment"
  },
  {
    "number": 12512,
    "action": "review_comment_synced",
    "reason": "updated durable Codex review comment"
  },
  {
    "number": 12554,
    "action": "review_comment_synced",
    "reason": "updated durable Codex review comment"
  },
  {
    "number": 12590,
    "action": "review_comment_synced",
    "reason": "updated durable Codex review comment"
  },
  {
    "number": 12602,
    "action": "review_comment_synced",
    "reason": "updated durable Codex review comment"
  },
  {
    "number": 12756,
    "action": "review_comment_synced",
    "reason": "updated durable Codex review comment"
  },
  {
    "number": 12831,
    "action": "review_comment_synced",
    "reason": "updated durable Codex review comment"
  },
  {
    "number": 13219,
    "action": "review_comment_synced",
    "reason": "updated durable Codex review comment"
  },
  {
    "number": 13241,
    "action": "review_comment_synced",
    "reason": "updated durable Codex review comment"
  },
  {
    "number": 13271,
    "action": "review_comment_synced",
    "reason": "updated durable Codex review comment"
  },
  {
    "number": 13304,
    "action": "review_comment_synced",
    "reason": "updated durable Codex review comment"
  },
  {
    "number": 13337,
    "action": "review_comment_synced",
    "reason": "updated durable Codex review comment"
  },
  {
    "number": 13362,
    "action": "review_comment_synced",
    "reason": "updated durable Codex review comment"
  },
  {
    "number": 13387,
    "action": "review_comment_synced",
    "reason": "updated durable Codex review comment"
  },
  {
    "number": 13417,
    "action": "review_comment_synced",
    "reason": "updated durable Codex review comment"
  },
  {
    "number": 13440,
    "action": "review_comment_synced",
    "reason": "updated durable Codex review comment"
  },
  {
    "number": 13479,
    "action": "review_comment_synced",
    "reason": "updated durable Codex review comment"
  },
  {
    "number": 13487,
    "action": "review_comment_synced",
    "reason": "updated durable Codex review comment"
  },
  {
    "number": 13543,
    "action": "review_comment_synced",
    "reason": "updated durable Codex review comment"
  },
  {
    "number": 13570,
    "action": "review_comment_synced",
    "reason": "updated durable Codex review comment"
  },
  {
    "number": 13583,
    "action": "review_comment_synced",
    "reason": "updated durable Codex review comment"
  },
  {
    "number": 13615,
    "action": "review_comment_synced",
    "reason": "updated durable Codex review comment"
  },
  {
    "number": 13617,
    "action": "review_comment_synced",
    "reason": "updated durable Codex review comment"
  },
  {
    "number": 13620,
    "action": "review_comment_synced",
    "reason": "updated durable Codex review comment"
  },
  {
    "number": 13627,
    "action": "review_comment_synced",
    "reason": "updated durable Codex review comment"
  },
  {
    "number": 13634,
    "action": "review_comment_synced",
    "reason": "updated durable Codex review comment"
  },
  {
    "number": 13676,
    "action": "review_comment_synced",
    "reason": "updated durable Codex review comment"
  },
  {
    "number": 13700,
    "action": "review_comment_synced",
    "reason": "updated durable Codex review comment"
  },
  {
    "number": 13744,
    "action": "review_comment_synced",
    "reason": "updated durable Codex review comment"
  },
  {
    "number": 13751,
    "action": "review_comment_synced",
    "reason": "updated durable Codex review comment"
  },
  {
    "number": 13870,
    "action": "review_comment_synced",
    "reason": "updated durable Codex review comment"
  },
  {
    "number": 13948,
    "action": "review_comment_synced",
    "reason": "updated durable Codex review comment"
  },
  {
    "number": 14079,
    "action": "review_comment_synced",
    "reason": "updated durable Codex review comment"
  },
  {
    "number": 14151,
    "action": "review_comment_synced",
    "reason": "updated durable Codex review comment"
  },
  {
    "number": 14206,
    "action": "review_comment_synced",
    "reason": "updated durable Codex review comment"
  },
  {
    "number": 14251,
    "action": "review_comment_synced",
    "reason": "updated durable Codex review comment"
  },
  {
    "number": 14317,
    "action": "review_comment_synced",
    "reason": "updated durable Codex review comment"
  },
  {
    "number": 14344,
    "action": "review_comment_synced",
    "reason": "updated durable Codex review comment"
  },
  {
    "number": 14526,
    "action": "review_comment_synced",
    "reason": "updated durable Codex review comment"
  },
  {
    "number": 14601,
    "action": "review_comment_synced",
    "reason": "updated durable Codex review comment"
  },
  {
    "number": 14629,
    "action": "review_comment_synced",
    "reason": "updated durable Codex review comment"
  },
  {
    "number": 14747,
    "action": "review_comment_synced",
    "reason": "updated durable Codex review comment"
  },
  {
    "number": 14785,
    "action": "review_comment_synced",
    "reason": "updated durable Codex review comment"
  },
  {
    "number": 14804,
    "action": "review_comment_synced",
    "reason": "updated durable Codex review comment"
  },
  {
    "number": 14850,
    "action": "review_comment_synced",
    "reason": "updated durable Codex review comment"
  },
  {
    "number": 14861,
    "action": "review_comment_synced",
    "reason": "updated durable Codex review comment"
  },
  {
    "number": 14874,
    "action": "review_comment_synced",
    "reason": "updated durable Codex review comment"
  },
  {
    "number": 14968,
    "action": "review_comment_synced",
    "reason": "updated durable Codex review comment"
  },
  {
    "number": 15828,
    "action": "review_comment_synced",
    "reason": "updated durable Codex review comment"
  },
  {
    "number": 16085,
    "action": "review_comment_synced",
    "reason": "updated durable Codex review comment"
  },
  {
    "number": 16121,
    "action": "review_comment_synced",
    "reason": "updated durable Codex review comment"
  },
  {
    "number": 16142,
    "action": "review_comment_synced",
    "reason": "updated durable Codex review comment"
  },
  {
    "number": 16387,
    "action": "review_comment_synced",
    "reason": "updated durable Codex review comment"
  },
  {
    "number": 16555,
    "action": "review_comment_synced",
    "reason": "updated durable Codex review comment"
  },
  {
    "number": 16670,
    "action": "review_comment_synced",
    "reason": "updated durable Codex review comment"
  },
  {
    "number": 16896,
    "action": "review_comment_synced",
    "reason": "updated durable Codex review comment"
  },
  {
    "number": 17810,
    "action": "review_comment_synced",
    "reason": "updated durable Codex review comment"
  },
  {
    "number": 17876,
    "action": "review_comment_synced",
    "reason": "updated durable Codex review comment"
  },
  {
    "number": 17925,
    "action": "review_comment_synced",
    "reason": "updated durable Codex review comment"
  },
  {
    "number": 18548,
    "action": "review_comment_synced",
    "reason": "updated durable Codex review comment"
  },
  {
    "number": 18985,
    "action": "review_comment_synced",
    "reason": "updated durable Codex review comment"
  },
  {
    "number": 19680,
    "action": "review_comment_synced",
    "reason": "updated durable Codex review comment"
  },
  {
    "number": 20237,
    "action": "review_comment_synced",
    "reason": "updated durable Codex review comment"
  },
  {
    "number": 20321,
    "action": "review_comment_synced",
    "reason": "updated durable Codex review comment"
  },
  {
    "number": 20950,
    "action": "review_comment_synced",
    "reason": "updated durable Codex review comment"
  },
  {
    "number": 22021,
    "action": "review_comment_synced",
    "reason": "updated durable Codex review comment"
  },
  {
    "number": 22438,
    "action": "review_comment_synced",
    "reason": "updated durable Codex review comment"
  },
  {
    "number": 23585,
    "action": "review_comment_synced",
    "reason": "updated durable Codex review comment"
  },
  {
    "number": 25295,
    "action": "review_comment_synced",
    "reason": "updated durable Codex review comment"
  },
  {
    "number": 26428,
    "action": "review_comment_synced",
    "reason": "updated durable Codex review comment"
  },
  {
    "number": 27137,
    "action": "review_comment_synced",
    "reason": "updated durable Codex review comment"
  },
  {
    "number": 29707,
    "action": "review_comment_synced",
    "reason": "updated durable Codex review comment"
  },
  {
    "number": 29736,
    "action": "review_comment_synced",
    "reason": "updated durable Codex review comment"
  },
  {
    "number": 32188,
    "action": "review_comment_synced",
    "reason": "updated durable Codex review comment"
  },
  {
    "number": 33845,
    "action": "review_comment_synced",
    "reason": "updated durable Codex review comment"
  },
  {
    "number": 36314,
    "action": "review_comment_synced",
    "reason": "updated durable Codex review comment"
  },
  {
    "number": 37589,
    "action": "review_comment_synced",
    "reason": "updated durable Codex review comment"
  },
  {
    "number": 38076,
    "action": "review_comment_synced",
    "reason": "updated durable Codex review comment"
  },
  {
    "number": 38501,
    "action": "review_comment_synced",
    "reason": "updated durable Codex review comment"
  },
  {
    "number": 38729,
    "action": "review_comment_synced",
    "reason": "updated durable Codex review comment"
  },
  {
    "number": 39038,
    "action": "review_comment_synced",
    "reason": "updated durable Codex review comment"
  },
  {
    "number": 39605,
    "action": "review_comment_synced",
    "reason": "updated durable Codex review comment"
  },
  {
    "number": 40220,
    "action": "review_comment_synced",
    "reason": "updated durable Codex review comment"
  },
  {
    "number": 40236,
    "action": "review_comment_synced",
    "reason": "updated durable Codex review comment"
  },
  {
    "number": 40238,
    "action": "review_comment_synced",
    "reason": "updated durable Codex review comment"
  },
  {
    "number": 40289,
    "action": "review_comment_synced",
    "reason": "updated durable Codex review comment"
  },
  {
    "number": 40290,
    "action": "review_comment_synced",
    "reason": "updated durable Codex review comment"
  },
  {
    "number": 40311,
    "action": "review_comment_synced",
    "reason": "updated durable Codex review comment"
  },
  {
    "number": 40332,
    "action": "review_comment_synced",
    "reason": "updated durable Codex review comment"
  },
  {
    "number": 40421,
    "action": "review_comment_synced",
    "reason": "updated durable Codex review comment"
  },
  {
    "number": 40438,
    "action": "review_comment_synced",
    "reason": "updated durable Codex review comment"
  },
  {
    "number": 40481,
    "action": "review_comment_synced",
    "reason": "updated durable Codex review comment"
  },
  {
    "number": 40527,
    "action": "review_comment_synced",
    "reason": "updated durable Codex review comment"
  },
  {
    "number": 40530,
    "action": "review_comment_synced",
    "reason": "updated durable Codex review comment"
  },
  {
    "number": 40534,
    "action": "review_comment_synced",
    "reason": "updated durable Codex review comment"
  },
  {
    "number": 40540,
    "action": "review_comment_synced",
    "reason": "updated durable Codex review comment"
  },
  {
    "number": 40618,
    "action": "review_comment_synced",
    "reason": "updated durable Codex review comment"
  },
  {
    "number": 40644,
    "action": "review_comment_synced",
    "reason": "updated durable Codex review comment"
  },
  {
    "number": 40652,
    "action": "review_comment_synced",
    "reason": "updated durable Codex review comment"
  },
  {
    "number": 40654,
    "action": "review_comment_synced",
    "reason": "updated durable Codex review comment"
  },
  {
    "number": 40665,
    "action": "review_comment_synced",
    "reason": "updated durable Codex review comment"
  },
  {
    "number": 40678,
    "action": "review_comment_synced",
    "reason": "updated durable Codex review comment"
  },
  {
    "number": 40697,
    "action": "review_comment_synced",
    "reason": "updated durable Codex review comment"
  },
  {
    "number": 40703,
    "action": "review_comment_synced",
    "reason": "updated durable Codex review comment"
  },
  {
    "number": 40747,
    "action": "review_comment_synced",
    "reason": "updated durable Codex review comment"
  },
  {
    "number": 40756,
    "action": "review_comment_synced",
    "reason": "updated durable Codex review comment"
  },
  {
    "number": 40782,
    "action": "review_comment_synced",
    "reason": "updated durable Codex review comment"
  },
  {
    "number": 40791,
    "action": "review_comment_synced",
    "reason": "updated durable Codex review comment"
  },
  {
    "number": 40820,
    "action": "review_comment_synced",
    "reason": "updated durable Codex review comment"
  },
  {
    "number": 40840,
    "action": "review_comment_synced",
    "reason": "updated durable Codex review comment"
  },
  {
    "number": 40847,
    "action": "review_comment_synced",
    "reason": "updated durable Codex review comment"
  },
  {
    "number": 40864,
    "action": "review_comment_synced",
    "reason": "updated durable Codex review comment"
  },
  {
    "number": 40945,
    "action": "review_comment_synced",
    "reason": "updated durable Codex review comment"
  },
  {
    "number": 40950,
    "action": "review_comment_synced",
    "reason": "updated durable Codex review comment"
  },
  {
    "number": 41037,
    "action": "review_comment_synced",
    "reason": "updated durable Codex review comment"
  },
  {
    "number": 41038,
    "action": "review_comment_synced",
    "reason": "updated durable Codex review comment"
  },
  {
    "number": 41067,
    "action": "review_comment_synced",
    "reason": "updated durable Codex review comment"
  },
  {
    "number": 41165,
    "action": "review_comment_synced",
    "reason": "updated durable Codex review comment"
  },
  {
    "number": 41201,
    "action": "review_comment_synced",
    "reason": "updated durable Codex review comment"
  },
  {
    "number": 41268,
    "action": "review_comment_synced",
    "reason": "updated durable Codex review comment"
  },
  {
    "number": 41320,
    "action": "review_comment_synced",
    "reason": "updated durable Codex review comment"
  },
  {
    "number": 41332,
    "action": "review_comment_synced",
    "reason": "updated durable Codex review comment"
  },
  {
    "number": 41559,
    "action": "review_comment_synced",
    "reason": "updated durable Codex review comment"
  },
  {
    "number": 41581,
    "action": "review_comment_synced",
    "reason": "updated durable Codex review comment"
  },
  {
    "number": 41621,
    "action": "review_comment_synced",
    "reason": "updated durable Codex review comment"
  },
  {
    "number": 41628,
    "action": "review_comment_synced",
    "reason": "updated durable Codex review comment"
  },
  {
    "number": 41637,
    "action": "review_comment_synced",
    "reason": "updated durable Codex review comment"
  },
  {
    "number": 41659,
    "action": "review_comment_synced",
    "reason": "updated durable Codex review comment"
  },
  {
    "number": 41660,
    "action": "review_comment_synced",
    "reason": "updated durable Codex review comment"
  },
  {
    "number": 41696,
    "action": "review_comment_synced",
    "reason": "updated durable Codex review comment"
  },
  {
    "number": 41851,
    "action": "review_comment_synced",
    "reason": "updated durable Codex review comment"
  },
  {
    "number": 41956,
    "action": "review_comment_synced",
    "reason": "updated durable Codex review comment"
  },
  {
    "number": 42544,
    "action": "review_comment_synced",
    "reason": "updated durable Codex review comment"
  },
  {
    "number": 42797,
    "action": "review_comment_synced",
    "reason": "updated durable Codex review comment"
  },
  {
    "number": 42819,
    "action": "review_comment_synced",
    "reason": "updated durable Codex review comment"
  },
  {
    "number": 42824,
    "action": "review_comment_synced",
    "reason": "updated durable Codex review comment"
  },
  {
    "number": 42856,
    "action": "review_comment_synced",
    "reason": "updated durable Codex review comment"
  },
  {
    "number": 42867,
    "action": "review_comment_synced",
    "reason": "updated durable Codex review comment"
  },
  {
    "number": 43063,
    "action": "review_comment_synced",
    "reason": "updated durable Codex review comment"
  },
  {
    "number": 43095,
    "action": "review_comment_synced",
    "reason": "updated durable Codex review comment"
  },
  {
    "number": 43246,
    "action": "review_comment_synced",
    "reason": "updated durable Codex review comment"
  },
  {
    "number": 43291,
    "action": "review_comment_synced",
    "reason": "updated durable Codex review comment"
  },
  {
    "number": 43295,
    "action": "review_comment_synced",
    "reason": "updated durable Codex review comment"
  },
  {
    "number": 43383,
    "action": "review_comment_synced",
    "reason": "updated durable Codex review comment"
  },
  {
    "number": 43390,
    "action": "review_comment_synced",
    "reason": "updated durable Codex review comment"
  },
  {
    "number": 43404,
    "action": "review_comment_synced",
    "reason": "updated durable Codex review comment"
  },
  {
    "number": 43410,
    "action": "review_comment_synced",
    "reason": "updated durable Codex review comment"
  },
  {
    "number": 43411,
    "action": "review_comment_synced",
    "reason": "updated durable Codex review comment"
  },
  {
    "number": 43416,
    "action": "review_comment_synced",
    "reason": "updated durable Codex review comment"
  },
  {
    "number": 43441,
    "action": "review_comment_synced",
    "reason": "updated durable Codex review comment"
  },
  {
    "number": 43443,
    "action": "review_comment_synced",
    "reason": "updated durable Codex review comment"
  },
  {
    "number": 43447,
    "action": "review_comment_synced",
    "reason": "updated durable Codex review comment"
  },
  {
    "number": 43455,
    "action": "review_comment_synced",
    "reason": "updated durable Codex review comment"
  },
  {
    "number": 43480,
    "action": "review_comment_synced",
    "reason": "updated durable Codex review comment"
  },
  {
    "number": 43481,
    "action": "review_comment_synced",
    "reason": "updated durable Codex review comment"
  },
  {
    "number": 43512,
    "action": "review_comment_synced",
    "reason": "updated durable Codex review comment"
  },
  {
    "number": 43527,
    "action": "review_comment_synced",
    "reason": "updated durable Codex review comment"
  },
  {
    "number": 43529,
    "action": "review_comment_synced",
    "reason": "updated durable Codex review comment"
  },
  {
    "number": 43557,
    "action": "review_comment_synced",
    "reason": "updated durable Codex review comment"
  },
  {
    "number": 43565,
    "action": "review_comment_synced",
    "reason": "updated durable Codex review comment"
  },
  {
    "number": 43567,
    "action": "review_comment_synced",
    "reason": "updated durable Codex review comment"
  },
  {
    "number": 43570,
    "action": "review_comment_synced",
    "reason": "updated durable Codex review comment"
  },
  {
    "number": 43573,
    "action": "review_comment_synced",
    "reason": "updated durable Codex review comment"
  },
  {
    "number": 43585,
    "action": "review_comment_synced",
    "reason": "updated durable Codex review comment"
  },
  {
    "number": 43609,
    "action": "review_comment_synced",
    "reason": "updated durable Codex review comment"
  },
  {
    "number": 43614,
    "action": "review_comment_synced",
    "reason": "updated durable Codex review comment"
  },
  {
    "number": 43618,
    "action": "review_comment_synced",
    "reason": "updated durable Codex review comment"
  },
  {
    "number": 43656,
    "action": "review_comment_synced",
    "reason": "updated durable Codex review comment"
  },
  {
    "number": 43679,
    "action": "review_comment_synced",
    "reason": "updated durable Codex review comment"
  },
  {
    "number": 43730,
    "action": "review_comment_synced",
    "reason": "updated durable Codex review comment"
  },
  {
    "number": 43737,
    "action": "review_comment_synced",
    "reason": "updated durable Codex review comment"
  },
  {
    "number": 43747,
    "action": "review_comment_synced",
    "reason": "updated durable Codex review comment"
  },
  {
    "number": 43752,
    "action": "review_comment_synced",
    "reason": "updated durable Codex review comment"
  },
  {
    "number": 43765,
    "action": "review_comment_synced",
    "reason": "updated durable Codex review comment"
  },
  {
    "number": 43791,
    "action": "review_comment_synced",
    "reason": "updated durable Codex review comment"
  },
  {
    "number": 43793,
    "action": "review_comment_synced",
    "reason": "updated durable Codex review comment"
  },
  {
    "number": 43795,
    "action": "review_comment_synced",
    "reason": "updated durable Codex review comment"
  },
  {
    "number": 43808,
    "action": "review_comment_synced",
    "reason": "updated durable Codex review comment"
  },
  {
    "number": 43827,
    "action": "review_comment_synced",
    "reason": "updated durable Codex review comment"
  },
  {
    "number": 43835,
    "action": "review_comment_synced",
    "reason": "updated durable Codex review comment"
  },
  {
    "number": 43848,
    "action": "review_comment_synced",
    "reason": "updated durable Codex review comment"
  },
  {
    "number": 43866,
    "action": "review_comment_synced",
    "reason": "updated durable Codex review comment"
  },
  {
    "number": 43895,
    "action": "review_comment_synced",
    "reason": "updated durable Codex review comment"
  },
  {
    "number": 43912,
    "action": "review_comment_synced",
    "reason": "updated durable Codex review comment"
  },
  {
    "number": 43935,
    "action": "review_comment_synced",
    "reason": "updated durable Codex review comment"
  },
  {
    "number": 43951,
    "action": "review_comment_synced",
    "reason": "updated durable Codex review comment"
  },
  {
    "number": 43975,
    "action": "review_comment_synced",
    "reason": "updated durable Codex review comment"
  },
  {
    "number": 43982,
    "action": "review_comment_synced",
    "reason": "updated durable Codex review comment"
  },
  {
    "number": 43992,
    "action": "review_comment_synced",
    "reason": "updated durable Codex review comment"
  },
  {
    "number": 43996,
    "action": "review_comment_synced",
    "reason": "updated durable Codex review comment"
  },
  {
    "number": 44013,
    "action": "review_comment_synced",
    "reason": "updated durable Codex review comment"
  },
  {
    "number": 44023,
    "action": "skipped_already_closed",
    "reason": "state is closed"
  },
  {
    "number": 44329,
    "action": "review_comment_synced",
    "reason": "updated durable Codex review comment"
  },
  {
    "number": 44395,
    "action": "review_comment_synced",
    "reason": "updated durable Codex review comment"
  },
  {
    "number": 44833,
    "action": "review_comment_synced",
    "reason": "updated durable Codex review comment"
  },
  {
    "number": 44870,
    "action": "review_comment_synced",
    "reason": "updated durable Codex review comment"
  },
  {
    "number": 44896,
    "action": "review_comment_synced",
    "reason": "updated durable Codex review comment"
  },
  {
    "number": 44905,
    "action": "review_comment_synced",
    "reason": "updated durable Codex review comment"
  },
  {
    "number": 44910,
    "action": "review_comment_synced",
    "reason": "updated durable Codex review comment"
  },
  {
    "number": 44922,
    "action": "review_comment_synced",
    "reason": "updated durable Codex review comment"
  },
  {
    "number": 44925,
    "action": "review_comment_synced",
    "reason": "updated durable Codex review comment"
  },
  {
    "number": 44941,
    "action": "review_comment_synced",
    "reason": "updated durable Codex review comment"
  },
  {
    "number": 44993,
    "action": "review_comment_synced",
    "reason": "updated durable Codex review comment"
  },
  {
    "number": 44996,
    "action": "review_comment_synced",
    "reason": "updated durable Codex review comment"
  },
  {
    "number": 45016,
    "action": "review_comment_synced",
    "reason": "updated durable Codex review comment"
  },
  {
    "number": 45020,
    "action": "review_comment_synced",
    "reason": "updated durable Codex review comment"
  },
  {
    "number": 45028,
    "action": "review_comment_synced",
    "reason": "updated durable Codex review comment"
  },
  {
    "number": 45031,
    "action": "review_comment_synced",
    "reason": "updated durable Codex review comment"
  },
  {
    "number": 45041,
    "action": "review_comment_synced",
    "reason": "updated durable Codex review comment"
  },
  {
    "number": 45049,
    "action": "review_comment_synced",
    "reason": "updated durable Codex review comment"
  },
  {
    "number": 45050,
    "action": "review_comment_synced",
    "reason": "updated durable Codex review comment"
  },
  {
    "number": 45179,
    "action": "review_comment_synced",
    "reason": "updated durable Codex review comment"
  },
  {
    "number": 45184,
    "action": "review_comment_synced",
    "reason": "updated durable Codex review comment"
  },
  {
    "number": 45210,
    "action": "review_comment_synced",
    "reason": "updated durable Codex review comment"
  },
  {
    "number": 45224,
    "action": "review_comment_synced",
    "reason": "updated durable Codex review comment"
  },
  {
    "number": 45269,
    "action": "review_comment_synced",
    "reason": "updated durable Codex review comment"
  },
  {
    "number": 45524,
    "action": "review_comment_synced",
    "reason": "updated durable Codex review comment"
  },
  {
    "number": 45530,
    "action": "review_comment_synced",
    "reason": "updated durable Codex review comment"
  },
  {
    "number": 45930,
    "action": "review_comment_synced",
    "reason": "updated durable Codex review comment"
  },
  {
    "number": 46023,
    "action": "review_comment_synced",
    "reason": "updated durable Codex review comment"
  },
  {
    "number": 46109,
    "action": "review_comment_synced",
    "reason": "updated durable Codex review comment"
  },
  {
    "number": 46168,
    "action": "review_comment_synced",
    "reason": "updated durable Codex review comment"
  },
  {
    "number": 46303,
    "action": "review_comment_synced",
    "reason": "updated durable Codex review comment"
  },
  {
    "number": 46544,
    "action": "review_comment_synced",
    "reason": "updated durable Codex review comment"
  },
  {
    "number": 46548,
    "action": "review_comment_synced",
    "reason": "updated durable Codex review comment"
  },
  {
    "number": 46593,
    "action": "review_comment_synced",
    "reason": "updated durable Codex review comment"
  },
  {
    "number": 46656,
    "action": "review_comment_synced",
    "reason": "updated durable Codex review comment"
  },
  {
    "number": 46786,
    "action": "review_comment_synced",
    "reason": "updated durable Codex review comment"
  },
  {
    "number": 46809,
    "action": "review_comment_synced",
    "reason": "updated durable Codex review comment"
  },
  {
    "number": 46812,
    "action": "review_comment_synced",
    "reason": "updated durable Codex review comment"
  },
  {
    "number": 46962,
    "action": "review_comment_synced",
    "reason": "updated durable Codex review comment"
  },
  {
    "number": 47143,
    "action": "review_comment_synced",
    "reason": "updated durable Codex review comment"
  },
  {
    "number": 47235,
    "action": "review_comment_synced",
    "reason": "updated durable Codex review comment"
  },
  {
    "number": 47452,
    "action": "review_comment_synced",
    "reason": "updated durable Codex review comment"
  },
  {
    "number": 47555,
    "action": "review_comment_synced",
    "reason": "updated durable Codex review comment"
  },
  {
    "number": 47565,
    "action": "review_comment_synced",
    "reason": "updated durable Codex review comment"
  },
  {
    "number": 47604,
    "action": "review_comment_synced",
    "reason": "updated durable Codex review comment"
  },
  {
    "number": 47663,
    "action": "review_comment_synced",
    "reason": "updated durable Codex review comment"
  },
  {
    "number": 47712,
    "action": "review_comment_synced",
    "reason": "updated durable Codex review comment"
  },
  {
    "number": 47723,
    "action": "review_comment_synced",
    "reason": "updated durable Codex review comment"
  },
  {
    "number": 47743,
    "action": "review_comment_synced",
    "reason": "updated durable Codex review comment"
  },
  {
    "number": 47856,
    "action": "review_comment_synced",
    "reason": "updated durable Codex review comment"
  },
  {
    "number": 47910,
    "action": "review_comment_synced",
    "reason": "updated durable Codex review comment"
  },
  {
    "number": 48133,
    "action": "review_comment_synced",
    "reason": "updated durable Codex review comment"
  },
  {
    "number": 48486,
    "action": "review_comment_synced",
    "reason": "updated durable Codex review comment"
  },
  {
    "number": 48606,
    "action": "review_comment_synced",
    "reason": "updated durable Codex review comment"
  },
  {
    "number": 48780,
    "action": "review_comment_synced",
    "reason": "updated durable Codex review comment"
  },
  {
    "number": 48785,
    "action": "review_comment_synced",
    "reason": "updated durable Codex review comment"
  },
  {
    "number": 48814,
    "action": "review_comment_synced",
    "reason": "updated durable Codex review comment"
  },
  {
    "number": 48920,
    "action": "review_comment_synced",
    "reason": "updated durable Codex review comment"
  },
  {
    "number": 49431,
    "action": "review_comment_synced",
    "reason": "updated durable Codex review comment"
  },
  {
    "number": 49931,
    "action": "review_comment_synced",
    "reason": "updated durable Codex review comment"
  },
  {
    "number": 50040,
    "action": "review_comment_synced",
    "reason": "updated durable Codex review comment"
  },
  {
    "number": 50103,
    "action": "review_comment_synced",
    "reason": "updated durable Codex review comment"
  },
  {
    "number": 50145,
    "action": "review_comment_synced",
    "reason": "updated durable Codex review comment"
  },
  {
    "number": 50165,
    "action": "review_comment_synced",
    "reason": "updated durable Codex review comment"
  },
  {
    "number": 50184,
    "action": "review_comment_synced",
    "reason": "updated durable Codex review comment"
  },
  {
    "number": 50199,
    "action": "review_comment_synced",
    "reason": "updated durable Codex review comment"
  },
  {
    "number": 50245,
    "action": "review_comment_synced",
    "reason": "updated durable Codex review comment"
  },
  {
    "number": 50276,
    "action": "review_comment_synced",
    "reason": "updated durable Codex review comment"
  },
  {
    "number": 50404,
    "action": "review_comment_synced",
    "reason": "updated durable Codex review comment"
  },
  {
    "number": 50481,
    "action": "review_comment_synced",
    "reason": "updated durable Codex review comment"
  },
  {
    "number": 50483,
    "action": "review_comment_synced",
    "reason": "updated durable Codex review comment"
  },
  {
    "number": 50611,
    "action": "review_comment_synced",
    "reason": "updated durable Codex review comment"
  },
  {
    "number": 50630,
    "action": "review_comment_synced",
    "reason": "updated durable Codex review comment"
  },
  {
    "number": 50887,
    "action": "review_comment_synced",
    "reason": "updated durable Codex review comment"
  },
  {
    "number": 50998,
    "action": "review_comment_synced",
    "reason": "updated durable Codex review comment"
  },
  {
    "number": 51011,
    "action": "review_comment_synced",
    "reason": "updated durable Codex review comment"
  },
  {
    "number": 51327,
    "action": "review_comment_synced",
    "reason": "updated durable Codex review comment"
  },
  {
    "number": 51706,
    "action": "review_comment_synced",
    "reason": "updated durable Codex review comment"
  },
  {
    "number": 52249,
    "action": "review_comment_synced",
    "reason": "updated durable Codex review comment"
  },
  {
    "number": 52401,
    "action": "review_comment_synced",
    "reason": "updated durable Codex review comment"
  },
  {
    "number": 52571,
    "action": "review_comment_synced",
    "reason": "updated durable Codex review comment"
  },
  {
    "number": 52664,
    "action": "review_comment_synced",
    "reason": "updated durable Codex review comment"
  },
  {
    "number": 52747,
    "action": "review_comment_synced",
    "reason": "updated durable Codex review comment"
  },
  {
    "number": 52759,
    "action": "review_comment_synced",
    "reason": "updated durable Codex review comment"
  },
  {
    "number": 52776,
    "action": "review_comment_synced",
    "reason": "updated durable Codex review comment"
  },
  {
    "number": 52861,
    "action": "review_comment_synced",
    "reason": "updated durable Codex review comment"
  },
  {
    "number": 52875,
    "action": "review_comment_synced",
    "reason": "updated durable Codex review comment"
  },
  {
    "number": 53023,
    "action": "review_comment_synced",
    "reason": "updated durable Codex review comment"
  },
  {
    "number": 53056,
    "action": "review_comment_synced",
    "reason": "updated durable Codex review comment"
  },
  {
    "number": 53092,
    "action": "review_comment_synced",
    "reason": "updated durable Codex review comment"
  },
  {
    "number": 53107,
    "action": "review_comment_synced",
    "reason": "updated durable Codex review comment"
  },
  {
    "number": 53145,
    "action": "review_comment_synced",
    "reason": "updated durable Codex review comment"
  },
  {
    "number": 53185,
    "action": "review_comment_synced",
    "reason": "updated durable Codex review comment"
  },
  {
    "number": 53198,
    "action": "review_comment_synced",
    "reason": "updated durable Codex review comment"
  },
  {
    "number": 53208,
    "action": "review_comment_synced",
    "reason": "updated durable Codex review comment"
  },
  {
    "number": 53228,
    "action": "review_comment_synced",
    "reason": "updated durable Codex review comment"
  },
  {
    "number": 53308,
    "action": "review_comment_synced",
    "reason": "updated durable Codex review comment"
  },
  {
    "number": 53316,
    "action": "review_comment_synced",
    "reason": "updated durable Codex review comment"
  },
  {
    "number": 53319,
    "action": "review_comment_synced",
    "reason": "updated durable Codex review comment"
  },
  {
    "number": 53345,
    "action": "review_comment_synced",
    "reason": "updated durable Codex review comment"
  },
  {
    "number": 53390,
    "action": "review_comment_synced",
    "reason": "updated durable Codex review comment"
  },
  {
    "number": 53399,
    "action": "review_comment_synced",
    "reason": "updated durable Codex review comment"
  },
  {
    "number": 53406,
    "action": "review_comment_synced",
    "reason": "updated durable Codex review comment"
  },
  {
    "number": 53439,
    "action": "review_comment_synced",
    "reason": "updated durable Codex review comment"
  },
  {
    "number": 53522,
    "action": "review_comment_synced",
    "reason": "updated durable Codex review comment"
  },
  {
    "number": 53540,
    "action": "review_comment_synced",
    "reason": "updated durable Codex review comment"
  },
  {
    "number": 53548,
    "action": "review_comment_synced",
    "reason": "updated durable Codex review comment"
  },
  {
    "number": 53550,
    "action": "review_comment_synced",
    "reason": "updated durable Codex review comment"
  },
  {
    "number": 53600,
    "action": "review_comment_synced",
    "reason": "updated durable Codex review comment"
  },
  {
    "number": 53628,
    "action": "review_comment_synced",
    "reason": "updated durable Codex review comment"
  },
  {
    "number": 53645,
    "action": "review_comment_synced",
    "reason": "updated durable Codex review comment"
  },
  {
    "number": 53654,
    "action": "review_comment_synced",
    "reason": "updated durable Codex review comment"
  },
  {
    "number": 53682,
    "action": "review_comment_synced",
    "reason": "updated durable Codex review comment"
  },
  {
    "number": 53684,
    "action": "review_comment_synced",
    "reason": "updated durable Codex review comment"
  },
  {
    "number": 53732,
    "action": "review_comment_synced",
    "reason": "updated durable Codex review comment"
  },
  {
    "number": 53763,
    "action": "review_comment_synced",
    "reason": "updated durable Codex review comment"
  },
  {
    "number": 53774,
    "action": "review_comment_synced",
    "reason": "updated durable Codex review comment"
  },
  {
    "number": 53798,
    "action": "review_comment_synced",
    "reason": "updated durable Codex review comment"
  },
  {
    "number": 53809,
    "action": "review_comment_synced",
    "reason": "updated durable Codex review comment"
  },
  {
    "number": 53810,
    "action": "review_comment_synced",
    "reason": "updated durable Codex review comment"
  },
  {
    "number": 53858,
    "action": "review_comment_synced",
    "reason": "updated durable Codex review comment"
  },
  {
    "number": 53942,
    "action": "skipped_already_closed",
    "reason": "state is closed"
  },
  {
    "number": 53958,
    "action": "review_comment_synced",
    "reason": "updated durable Codex review comment"
  },
  {
    "number": 53982,
    "action": "review_comment_synced",
    "reason": "updated durable Codex review comment"
  },
  {
    "number": 0,
    "action": "skipped_runtime_budget",
    "reason": "max runtime 720000ms reached"
  }
]